setup.py
asyncrequests/__init__.py
asyncrequests/file.py
asyncrequests.egg-info/PKG-INFO
asyncrequests.egg-info/SOURCES.txt
asyncrequests.egg-info/dependency_links.txt
asyncrequests.egg-info/requires.txt
asyncrequests.egg-info/top_level.txt