Metadata-Version: 1.1
Name: asyncrequests
Version: 0.1.1
Summary: Asynchronous Http Client for asyncio
Home-page: https://github.com/RevengeComing/asyncrequests
Author: Sepehr Hamzelooy
Author-email: s.hamzelooy@gmail.com
License: MIT
Keywords: requests http client
Platform: UNKNOWN
Classifier: Development Status :: 3 - Alpha
Classifier: Intended Audience :: Developers
Classifier: License :: OSI Approved :: MIT License
Classifier: Programming Language :: Python :: 3.5
